main.py
moreau-0.1.0.dist-info/METADATA
moreau-0.1.0.dist-info/WHEEL
moreau-0.1.0.dist-info/top_level.txt
moreau-0.1.0.dist-info/RECORD
