Metadata-Version: 2.4
Name: moreau
Version: 0.1.0
Summary: Applies the Moreau decomposition
Requires-Python: >=3.12
